koala_publisher/__init__.py
koala_publisher/graph_object_publisher.py
koala_publisher/utils.py
koala_publisher/exceptions/__init__.py
koala_publisher/exceptions/exceptions.py
koala_publisher-0.1.3.dist-info/METADATA
koala_publisher-0.1.3.dist-info/WHEEL
koala_publisher-0.1.3.dist-info/top_level.txt
koala_publisher-0.1.3.dist-info/RECORD
